shove_leveldb/__init__.py
shove_leveldb/store.py
shove_leveldb/test/__init__.py
shove_leveldb/test/test_ldbstore.py
shove_leveldb-0.1.1.dist-info/DESCRIPTION.rst
shove_leveldb-0.1.1.dist-info/METADATA
shove_leveldb-0.1.1.dist-info/RECORD
shove_leveldb-0.1.1.dist-info/WHEEL
shove_leveldb-0.1.1.dist-info/entry_points.txt
shove_leveldb-0.1.1.dist-info/metadata.json
shove_leveldb-0.1.1.dist-info/pbr.json
shove_leveldb-0.1.1.dist-info/top_level.txt
