Metadata-Version: 2.0
Name: shove-leveldb
Version: 0.1.1
Summary: Object storage frontend using LevelDB
Home-page: https://bitbucket.org/lcrees/shove-leveldb
Author: L. C. Rees
Author-email: lcrees@gmail.com
License: BSD
Keywords: object storage persistence database leveldb
Platform: UNKNOWN
Classifier: Development Status :: 4 - Beta
Classifier: Environment :: Web Environment
Classifier: License :: OSI Approved :: BSD License
Classifier: Operating System :: OS Independent
Classifier: Programming Language :: Python
Classifier: Topic :: Database :: Front-Ends
Classifier: Programming Language :: Python
Classifier: Programming Language :: Python :: 2.6
Classifier: Programming Language :: Python :: 2.7
Requires-Dist: shove (>=0.6.4)
Requires-Dist: leveldb
